zabob_houdini/__init__.py
zabob_houdini/__main__.py
zabob_houdini/__version__.py
zabob_houdini/cli.py
zabob_houdini/core.py
zabob_houdini/houdini_bridge.py
zabob_houdini/houdini_config.py
zabob_houdini/houdini_functions.py
zabob_houdini/houdini_info.py
zabob_houdini/houdini_test_functions.py
zabob_houdini/houdini_versions.py
zabob_houdini/package_installer.py
zabob_houdini/utils.py
zabob_houdini-0.1.3.dist-info/METADATA
zabob_houdini-0.1.3.dist-info/WHEEL
zabob_houdini-0.1.3.dist-info/entry_points.txt
zabob_houdini-0.1.3.dist-info/licenses/LICENSE
zabob_houdini-0.1.3.dist-info/RECORD
