Metadata-Version: 2.4
Name: zabob-houdini
Version: 0.1.3
Summary: A simple API for creating Houdini node graphs programmatically
Project-URL: Homepage, https://github.com/BobKerns/zabob-houdini
Project-URL: Repository, https://github.com/BobKerns/zabob-houdini
Project-URL: Issues, https://github.com/BobKerns/zabob-houdini/issues
Project-URL: Documentation, https://github.com/BobKerns/zabob-houdini#readme
Author-email: Bob Kerns <1154903+BobKerns@users.noreply.github.com>
License: MIT
License-File: LICENSE
Keywords: 3d,graphics,houdini,node-graph,procedural,vfx
Classifier: Development Status :: 3 - Alpha
Classifier: Intended Audience :: Developers
Classifier: License :: OSI Approved :: MIT License
Classifier: Programming Language :: Python :: 3
Classifier: Programming Language :: Python :: 3.11
Classifier: Programming Language :: Python :: 3.12
Classifier: Programming Language :: Python :: 3.13
Classifier: Programming Language :: Python :: 3.14
Classifier: Topic :: Multimedia :: Graphics :: 3D Modeling
Classifier: Topic :: Software Development :: Libraries :: Python Modules
Requires-Python: >=3.11
Requires-Dist: charset-normalizer<3.4.0
Requires-Dist: click>=8.0.0
Requires-Dist: pytest>=7.0.0
Requires-Dist: python-dotenv>=1.0.0
Requires-Dist: requests>=2.32.5
Requires-Dist: semver>=3.0.4
